air_sdk/__init__.py
air_sdk/account.py
air_sdk/air_api.py
air_sdk/air_model.py
air_sdk/capacity.py
air_sdk/const.py
air_sdk/demo.py
air_sdk/exceptions.py
air_sdk/fleet.py
air_sdk/image.py
air_sdk/interface.py
air_sdk/job.py
air_sdk/link.py
air_sdk/logger.py
air_sdk/login.py
air_sdk/marketplace.py
air_sdk/node.py
air_sdk/organization.py
air_sdk/permission.py
air_sdk/resource_budget.py
air_sdk/service.py
air_sdk/simulation.py
air_sdk/simulation_interface.py
air_sdk/simulation_node.py
air_sdk/ssh_key.py
air_sdk/token.py
air_sdk/topology.py
air_sdk/topology_file.py
air_sdk/user_preference.py
air_sdk/userconfig.py
air_sdk/util.py
air_sdk/v2/__init__.py
air_sdk/v2/air_json_encoder.py
air_sdk/v2/air_model.py
air_sdk/v2/client.py
air_sdk/v2/endpoints/__init__.py
air_sdk/v2/endpoints/accounts.py
air_sdk/v2/endpoints/announcements.py
air_sdk/v2/endpoints/api_tokens.py
air_sdk/v2/endpoints/cloud_inits.py
air_sdk/v2/endpoints/images.py
air_sdk/v2/endpoints/interfaces.py
air_sdk/v2/endpoints/jobs.py
air_sdk/v2/endpoints/manifests.py
air_sdk/v2/endpoints/marketplace_demo_tags.py
air_sdk/v2/endpoints/marketplace_demos.py
air_sdk/v2/endpoints/mixins.py
air_sdk/v2/endpoints/nodes.py
air_sdk/v2/endpoints/organizations.py
air_sdk/v2/endpoints/resource_budgets.py
air_sdk/v2/endpoints/services.py
air_sdk/v2/endpoints/simulations.py
air_sdk/v2/endpoints/systems.py
air_sdk/v2/endpoints/topologies.py
air_sdk/v2/endpoints/user_configs.py
air_sdk/v2/endpoints/workers.py
air_sdk/v2/exceptions.py
air_sdk/v2/typing.py
air_sdk/v2/utils.py
air_sdk/worker.py
air_sdk-3.0.0.dist-info/LICENSE
air_sdk-3.0.0.dist-info/METADATA
air_sdk-3.0.0.dist-info/WHEEL
air_sdk-3.0.0.dist-info/RECORD
