Metadata-Version: 2.1
Name: air-sdk
Version: 3.0.0
Summary: Python SDK for interacting with NVIDIA Air
Home-page: https://github.com/NVIDIA/air_sdk
License: MIT
Author: NVIDIA Air
Author-email: air-support@nvidia.com
Requires-Python: >=3.8,<4.0
Classifier: License :: OSI Approved :: MIT License
Classifier: Operating System :: OS Independent
Classifier: Programming Language :: Python :: 3
Classifier: Programming Language :: Python :: 3.8
Classifier: Programming Language :: Python :: 3.9
Classifier: Programming Language :: Python :: 3.10
Classifier: Programming Language :: Python :: 3.11
Classifier: Programming Language :: Python :: 3.12
Classifier: Programming Language :: Python :: 3.13
Requires-Dist: python-dateutil (>=2.9.0,<3.0.0)
Requires-Dist: requests (>=2.32.3,<3.0.0)
Project-URL: Bug Tracker, https://github.com/NVIDIA/air_sdk/issues
Project-URL: Homepage, https://github.com/NVIDIA/air_sdk/issues
